<?xml version="1.0" encoding="utf-8" ?>
<pizzas>
  <pizza name="Hawaii" id="1" addprice="1000">
    <toppings>
      <topping id="1" />
      <topping id="2" />
    </toppings>
  </pizza>
  <pizza name="pepperoni" id="2" addprice="800">
    <toppings>
      <topping id="5" />
      <topping id="2" />
    </toppings>
  </pizza>
  <pizza name="szalámis" id="3" addprice="800">
    <toppings>
      <topping id="4" />
    </toppings>
  </pizza>
  <pizza name="sonkás gombás" id="4" addprice="1000">
    <toppings>
      <topping id="2" />
      <topping id="3" />
    </toppings>
  </pizza>
</pizzas>